core/__init__.py
core/autograd.py
core/ops.py
core/tensor.py
nn/__init__.py
nn/functional.py
nn/layers.py
nn/optim.py
utils/__init__.py
utils/dataloader.py
asfenix_cpu-0.1.0.dist-info/METADATA
asfenix_cpu-0.1.0.dist-info/WHEEL
asfenix_cpu-0.1.0.dist-info/top_level.txt
asfenix_cpu-0.1.0.dist-info/RECORD
