Metadata-Version: 2.4
Name: asfenix-cpu
Version: 0.1.0
Summary: Framework de IA ligero y optimizado para CPU
Author: Tu Nombre
Author-email: Tu Nombre <tuemail@example.com>
License-Expression: MIT
Requires-Python: >=3.8
Requires-Dist: numpy
Requires-Dist: numba
Dynamic: author
Dynamic: requires-python
